imagery/__init__.py
imagery/gms_python.py
imagery/img_transformer.py
imagery/matcher_config.py
imagery/operations.py
imagery/pixel.py
imagery/post_process_sign.py
imagery/postprocessor.py
imagery/preprocess.py
imagery/reflection.py
imagery/util.py
imagery/utilities.py
imagery_mapilio-0.0.27.dist-info/METADATA
imagery_mapilio-0.0.27.dist-info/WHEEL
imagery_mapilio-0.0.27.dist-info/top_level.txt
imagery_mapilio-0.0.27.dist-info/RECORD
