Metadata-Version: 2.1
Name: imagery-mapilio
Version: 0.0.27
Summary: Mapilio Imagery Library
Home-page: https://github.com/mapilio/imagery.git
Author: Mapilio - Ozcan Durak
Author-email: ozcan@visiosoft.com.tr
License: MIT
Project-URL: Bug Reports, https://github.com/mapilio/imagery-tools/issues
Project-URL: Say Thanks!, https://mapilio.com/#contact
Project-URL: Source, https://github.com/mapilio/imagery-tools/
Requires-Python: >=3.6, <4
Requires-Dist: opencv-python
Requires-Dist: scipy
Requires-Dist: scikit-image
Requires-Dist: pandas
